{
    "prepare_queue": {
        "installed": [],
        "uninstalled": []
    },
    "config_munge": {
        "files": {}
    },
    "installed_plugins": {
        "cordova-plugin-console": {
            "PACKAGE_NAME": "com.skawa.jegyfigyelo"
        },
        "cordova-plugin-network-information": {
            "PACKAGE_NAME": "com.skawa.jegyfigyelo"
        },
        "cordova-plugin-vibration": {
            "PACKAGE_NAME": "com.skawa.jegyfigyelo"
        },
        "cordova-plugin-whitelist": {
            "PACKAGE_NAME": "com.skawa.jegyfigyelo"
        },
        "phonegap-plugin-push": {
            "SENDER_ID": "582404099538",
            "PACKAGE_NAME": "com.skawa.jegyfigyelo"
        }
    },
    "dependent_plugins": {}
}